mosaik_influxdb.py
integration_test/__init__.py
integration_test/collector.py
integration_test/controller.py
integration_test/demo_influxdb.py
integration_test/simulator.py
integration_test/simulator_mosaik.py
mosaik_influxdb-0.9.dist-info/AUTHORS.txt
mosaik_influxdb-0.9.dist-info/LICENSE.txt
mosaik_influxdb-0.9.dist-info/METADATA
mosaik_influxdb-0.9.dist-info/WHEEL
mosaik_influxdb-0.9.dist-info/entry_points.txt
mosaik_influxdb-0.9.dist-info/top_level.txt
mosaik_influxdb-0.9.dist-info/RECORD
